odoo/addons/sale_tier_validation/README.rst
odoo/addons/sale_tier_validation/__init__.py
odoo/addons/sale_tier_validation/__manifest__.py
odoo/addons/sale_tier_validation/data/mail_data.xml
odoo/addons/sale_tier_validation/i18n/es.po
odoo/addons/sale_tier_validation/i18n/es_MX.po
odoo/addons/sale_tier_validation/i18n/it.po
odoo/addons/sale_tier_validation/i18n/pt.po
odoo/addons/sale_tier_validation/i18n/sale_tier_validation.pot
odoo/addons/sale_tier_validation/i18n/sv.po
odoo/addons/sale_tier_validation/i18n/tr.po
odoo/addons/sale_tier_validation/i18n/zh_CN.po
odoo/addons/sale_tier_validation/models/__init__.py
odoo/addons/sale_tier_validation/models/res_company.py
odoo/addons/sale_tier_validation/models/res_config_settings.py
odoo/addons/sale_tier_validation/models/sale_order.py
odoo/addons/sale_tier_validation/models/tier_definition.py
odoo/addons/sale_tier_validation/readme/CONFIGURE.md
odoo/addons/sale_tier_validation/readme/CONTRIBUTORS.md
odoo/addons/sale_tier_validation/readme/DESCRIPTION.md
odoo/addons/sale_tier_validation/readme/INSTALL.md
odoo/addons/sale_tier_validation/readme/ROADMAP.md
odoo/addons/sale_tier_validation/readme/USAGE.md
odoo/addons/sale_tier_validation/reports/__init__.py
odoo/addons/sale_tier_validation/reports/sale_report.py
odoo/addons/sale_tier_validation/static/description/icon.png
odoo/addons/sale_tier_validation/static/description/index.html
odoo/addons/sale_tier_validation/tests/__init__.py
odoo/addons/sale_tier_validation/tests/test_tier_validation.py
odoo/addons/sale_tier_validation/views/res_config_settings_views.xml
odoo/addons/sale_tier_validation/views/sale_order_view.xml
odoo_addon_sale_tier_validation-18.0.1.0.0.3.dist-info/METADATA
odoo_addon_sale_tier_validation-18.0.1.0.0.3.dist-info/WHEEL
odoo_addon_sale_tier_validation-18.0.1.0.0.3.dist-info/top_level.txt
odoo_addon_sale_tier_validation-18.0.1.0.0.3.dist-info/RECORD
